<annotation>
        <folder>/Users/shivanshverma/NEU/Course Work/SML/Project/BCCD_Dataset-master/BCCD/Augmented</folder>
        <filename>BloodImage_00383_aug1.jpg</filename>
        <path>BloodImage_00383_aug1.jpg</path>
        <source>
                <database>Unknown</database>
        </source>
        <size>
                <width>640</width>
                <height>480</height>
                <depth>3</depth>
        </size>
 <object>
                <name>RBC</name>
                <pose>Unspecified</pose>
                <truncated>0</truncated>
                <difficult>0</difficult>
                <bndbox>
                        <xmin>545</xmin>
                        <ymin>230</ymin>
                        <xmax>640</xmax>
                        <ymax>338</ymax>
                </bndbox>
        </object>
 <object>
                <name>RBC</name>
                <pose>Unspecified</pose>
                <truncated>0</truncated>
                <difficult>0</difficult>
                <bndbox>
                        <xmin>158</xmin>
                        <ymin>20</ymin>
                        <xmax>291</xmax>
                        <ymax>169</ymax>
                </bndbox>
        </object>
 <object>
                <name>RBC</name>
                <pose>Unspecified</pose>
                <truncated>0</truncated>
                <difficult>0</difficult>
                <bndbox>
                        <xmin>0</xmin>
                        <ymin>162</ymin>
                        <xmax>129</xmax>
                        <ymax>310</ymax>
                </bndbox>
        </object>
 <object>
                <name>RBC</name>
                <pose>Unspecified</pose>
                <truncated>0</truncated>
                <difficult>0</difficult>
                <bndbox>
                        <xmin>643</xmin>
                        <ymin>0</ymin>
                        <xmax>640</xmax>
                        <ymax>108</ymax>
                </bndbox>
        </object>
 <object>
                <name>RBC</name>
                <pose>Unspecified</pose>
                <truncated>0</truncated>
                <difficult>0</difficult>
                <bndbox>
                        <xmin>522</xmin>
                        <ymin>0</ymin>
                        <xmax>640</xmax>
                        <ymax>133</ymax>
                </bndbox>
        </object>
 <object>
                <name>RBC</name>
                <pose>Unspecified</pose>
                <truncated>0</truncated>
                <difficult>0</difficult>
                <bndbox>
                        <xmin>545</xmin>
                        <ymin>76</ymin>
                        <xmax>640</xmax>
                        <ymax>220</ymax>
                </bndbox>
        </object>
 <object>
                <name>RBC</name>
                <pose>Unspecified</pose>
                <truncated>0</truncated>
                <difficult>0</difficult>
                <bndbox>
                        <xmin>629</xmin>
                        <ymin>330</ymin>
                        <xmax>640</xmax>
                        <ymax>463</ymax>
                </bndbox>
        </object>
 <object>
                <name>RBC</name>
                <pose>Unspecified</pose>
                <truncated>0</truncated>
                <difficult>0</difficult>
                <bndbox>
                        <xmin>251</xmin>
                        <ymin>0</ymin>
                        <xmax>385</xmax>
                        <ymax>16</ymax>
                </bndbox>
        </object>
 <object>
                <name>Platelets</name>
                <pose>Unspecified</pose>
                <truncated>0</truncated>
                <difficult>0</difficult>
                <bndbox>
                        <xmin>670</xmin>
                        <ymin>184</ymin>
                        <xmax>640</xmax>
                        <ymax>242</ymax>
                </bndbox>
        </object>
 <object>
                <name>Platelets</name>
                <pose>Unspecified</pose>
                <truncated>0</truncated>
                <difficult>0</difficult>
                <bndbox>
                        <xmin>475</xmin>
                        <ymin>168</ymin>
                        <xmax>537</xmax>
                        <ymax>219</ymax>
                </bndbox>
        </object>
 <object>
                <name>Platelets</name>
                <pose>Unspecified</pose>
                <truncated>0</truncated>
                <difficult>0</difficult>
                <bndbox>
                        <xmin>666</xmin>
                        <ymin>0</ymin>
                        <xmax>640</xmax>
                        <ymax>-55</ymax>
                </bndbox>
        </object>
 <object>
                <name>WBC</name>
                <pose>Unspecified</pose>
                <truncated>0</truncated>
                <difficult>0</difficult>
                <bndbox>
                        <xmin>116</xmin>
                        <ymin>173</ymin>
                        <xmax>486</xmax>
                        <ymax>480</ymax>
                </bndbox>
        </object>
</annotation>        
